LICENSE
README.md
setup.py
subdominator/__init__.py
subdominator/subdominator.py
subdominator.egg-info/PKG-INFO
subdominator.egg-info/SOURCES.txt
subdominator.egg-info/dependency_links.txt
subdominator.egg-info/entry_points.txt
subdominator.egg-info/requires.txt
subdominator.egg-info/top_level.txt
subdominator/modules/__init__.py
subdominator/modules/handler.py
subdominator/modules/banner/__init__.py
subdominator/modules/banner/banner.py
subdominator/modules/cli/__init__.py
subdominator/modules/cli/cli.py
subdominator/modules/config/__init__.py
subdominator/modules/config/config.py
subdominator/modules/crud/__init__.py
subdominator/modules/crud/crud.py
subdominator/modules/help/__init__.py
subdominator/modules/help/help.py
subdominator/modules/logger/__init__.py
subdominator/modules/logger/logger.py
subdominator/modules/models/__init__.py
subdominator/modules/models/models.py
subdominator/modules/notify/__init__.py
subdominator/modules/notify/notify.py
subdominator/modules/save/__init__.py
subdominator/modules/save/save.py
subdominator/modules/shell/__init__.py
subdominator/modules/shell/shell.py
subdominator/modules/source/__init__.py
subdominator/modules/source/source.py
subdominator/modules/subscraper/__init__.py
subdominator/modules/subscraper/abuseipdb/__init__.py
subdominator/modules/subscraper/abuseipdb/abuseipdb.py
subdominator/modules/subscraper/alienvault/__init__.py
subdominator/modules/subscraper/alienvault/alientvault.py
subdominator/modules/subscraper/anubis/__init__.py
subdominator/modules/subscraper/anubis/anubis.py
subdominator/modules/subscraper/arpsyndicate/__init__.py
subdominator/modules/subscraper/arpsyndicate/arpsyndicate.py
subdominator/modules/subscraper/bevigil/__init__.py
subdominator/modules/subscraper/bevigil/bevigil.py
subdominator/modules/subscraper/binaryedge/__init__.py
subdominator/modules/subscraper/binaryedge/binaryedge.py
subdominator/modules/subscraper/bufferover/__init__.py
subdominator/modules/subscraper/bufferover/bufferover.py
subdominator/modules/subscraper/builtwith/__init__.py
subdominator/modules/subscraper/builtwith/builtwith.py
subdominator/modules/subscraper/c99/__init__.py
subdominator/modules/subscraper/c99/c99.py
