Metadata-Version: 2.4
Name: subdominator
Version: 2.1.0
Summary: Subdominator - An ultimate subdomain enumeration tool for Security Researchers and Bug Bounty Hunters
Home-page: https://github.com/RevoltSecurities/Subdominator
Author: D. Sanjai Kumar
Author-email: bughunterz0047@gmail.com
License-File: LICENSE
Requires-Dist: aiofiles>=24.1.0
Requires-Dist: aiohttp>=3.10.11
Requires-Dist: appdirs>=1.4.4
Requires-Dist: art>=6.4
Requires-Dist: beautifulsoup4>=4.13.3
Requires-Dist: colorama>=0.4.6
Requires-Dist: fake_useragent>=2.0.3
Requires-Dist: httpx>=0.28.1
Requires-Dist: Jinja2>=3.1.6
Requires-Dist: prompt_toolkit>=3.0.50
Requires-Dist: PyYAML>=6.0.2
Requires-Dist: Requests>=2.32.3
Requires-Dist: rich>=13.9.4
Requires-Dist: setuptools>=75.6.0
Requires-Dist: SQLAlchemy>=2.0.32
Requires-Dist: tldextract>=5.1.2
Requires-Dist: weasyprint>=65.0
Dynamic: author
Dynamic: author-email
Dynamic: description
Dynamic: description-content-type
Dynamic: home-page
Dynamic: license-file
Dynamic: requires-dist
Dynamic: summary
